texts/__init__.py
texts/texts.py
noveltexts-0.1.1.dist-info/LICENSE
noveltexts-0.1.1.dist-info/METADATA
noveltexts-0.1.1.dist-info/WHEEL
noveltexts-0.1.1.dist-info/top_level.txt
noveltexts-0.1.1.dist-info/RECORD
