Metadata-Version: 2.1
Name: noveltexts
Version: 0.1.1
Summary: voice to text
Author-email: prajil <prajiltpriyan@example.com>
Classifier: Programming Language :: Python :: 3
Classifier: License :: OSI Approved :: MIT License
Classifier: Operating System :: OS Independent
Requires-Python: >=3.7
License-File: LICENSE
